<?xml version="1.0" encoding="UTF-8" standalone="yes"?><p:sld xmlns:a="http://schemas.openxmlformats.org/drawingml/2006/main" xmlns:r="http://schemas.openxmlformats.org/officeDocument/2006/relationships" xmlns:mc="http://schemas.openxmlformats.org/markup-compatibility/2006" xmlns:mv="urn:schemas-microsoft-com:mac:vml" xmlns:p="http://schemas.openxmlformats.org/presentationml/2006/main" xmlns:c="http://schemas.openxmlformats.org/drawingml/2006/chart" xmlns:dgm="http://schemas.openxmlformats.org/drawingml/2006/diagram" xmlns:o="urn:schemas-microsoft-com:office:office" xmlns:v="urn:schemas-microsoft-com:vml" xmlns:pvml="urn:schemas-microsoft-com:office:powerpoint" xmlns:com="http://schemas.openxmlformats.org/drawingml/2006/compatibility" xmlns:p14="http://schemas.microsoft.com/office/powerpoint/2010/main" xmlns:p15="http://schemas.microsoft.com/office/powerpoint/2012/main" xmlns:ahyp="http://schemas.microsoft.com/office/drawing/2018/hyperlinkcolor"><p:cSld><p:spTree><p:nvGrpSpPr><p:cNvPr id="413" name="Shape 413"/><p:cNvGrpSpPr/><p:nvPr/></p:nvGrpSpPr><p:grpSpPr><a:xfrm><a:off x="0" y="0"/><a:ext cx="0" cy="0"/><a:chOff x="0" y="0"/><a:chExt cx="0" cy="0"/></a:xfrm></p:grpSpPr><p:pic><p:nvPicPr><p:cNvPr id="414" name="Google Shape;414;p25" title="Gráfico"><a:hlinkClick r:id="rId3"/></p:cNvPr><p:cNvPicPr preferRelativeResize="0"/><p:nvPr/></p:nvPicPr><p:blipFill rotWithShape="1"><a:blip r:embed="rId4"><a:alphaModFix/></a:blip><a:srcRect b="7998" l="6260" r="2606" t="27393"/><a:stretch/></p:blipFill><p:spPr><a:xfrm><a:off x="774200" y="1188325"/><a:ext cx="7595600" cy="2588651"/></a:xfrm><a:prstGeom prst="rect"><a:avLst/></a:prstGeom><a:noFill/><a:ln><a:noFill/></a:ln></p:spPr></p:pic><p:grpSp><p:nvGrpSpPr><p:cNvPr id="415" name="Google Shape;415;p25"/><p:cNvGrpSpPr/><p:nvPr/></p:nvGrpSpPr><p:grpSpPr><a:xfrm><a:off x="-8162045" y="1212550"/><a:ext cx="7295938" cy="2275500"/><a:chOff x="2665325" y="1137775"/><a:chExt cx="3876900" cy="2275500"/></a:xfrm></p:grpSpPr><p:cxnSp><p:nvCxnSpPr><p:cNvPr id="416" name="Google Shape;416;p25"/><p:cNvCxnSpPr/><p:nvPr/></p:nvCxnSpPr><p:spPr><a:xfrm><a:off x="2665325" y="1137775"/><a:ext cx="3876900" cy="0"/></a:xfrm><a:prstGeom prst="straightConnector1"><a:avLst/></a:prstGeom><a:noFill/><a:ln cap="flat" cmpd="sng" w="9525"><a:solidFill><a:schemeClr val="dk2"/></a:solidFill><a:prstDash val="dot"/><a:round/><a:headEnd len="med" w="med" type="none"/><a:tailEnd len="med" w="med" type="none"/></a:ln></p:spPr></p:cxnSp><p:cxnSp><p:nvCxnSpPr><p:cNvPr id="417" name="Google Shape;417;p25"/><p:cNvCxnSpPr/><p:nvPr/></p:nvCxnSpPr><p:spPr><a:xfrm><a:off x="2665325" y="1365325"/><a:ext cx="3876900" cy="0"/></a:xfrm><a:prstGeom prst="straightConnector1"><a:avLst/></a:prstGeom><a:noFill/><a:ln cap="flat" cmpd="sng" w="9525"><a:solidFill><a:schemeClr val="dk2"/></a:solidFill><a:prstDash val="dot"/><a:round/><a:headEnd len="med" w="med" type="none"/><a:tailEnd len="med" w="med" type="none"/></a:ln></p:spPr></p:cxnSp><p:cxnSp><p:nvCxnSpPr><p:cNvPr id="418" name="Google Shape;418;p25"/><p:cNvCxnSpPr/><p:nvPr/></p:nvCxnSpPr><p:spPr><a:xfrm><a:off x="2665325" y="1592875"/><a:ext cx="3876900" cy="0"/></a:xfrm><a:prstGeom prst="straightConnector1"><a:avLst/></a:prstGeom><a:noFill/><a:ln cap="flat" cmpd="sng" w="9525"><a:solidFill><a:schemeClr val="dk2"/></a:solidFill><a:prstDash val="dot"/><a:round/><a:headEnd len="med" w="med" type="none"/><a:tailEnd len="med" w="med" type="none"/></a:ln></p:spPr></p:cxnSp><p:cxnSp><p:nvCxnSpPr><p:cNvPr id="419" name="Google Shape;419;p25"/><p:cNvCxnSpPr/><p:nvPr/></p:nvCxnSpPr><p:spPr><a:xfrm><a:off x="2665325" y="1820425"/><a:ext cx="3876900" cy="0"/></a:xfrm><a:prstGeom prst="straightConnector1"><a:avLst/></a:prstGeom><a:noFill/><a:ln cap="flat" cmpd="sng" w="9525"><a:solidFill><a:schemeClr val="dk2"/></a:solidFill><a:prstDash val="dot"/><a:round/><a:headEnd len="med" w="med" type="none"/><a:tailEnd len="med" w="med" type="none"/></a:ln></p:spPr></p:cxnSp><p:cxnSp><p:nvCxnSpPr><p:cNvPr id="420" name="Google Shape;420;p25"/><p:cNvCxnSpPr/><p:nvPr/></p:nvCxnSpPr><p:spPr><a:xfrm><a:off x="2665325" y="2047975"/><a:ext cx="3876900" cy="0"/></a:xfrm><a:prstGeom prst="straightConnector1"><a:avLst/></a:prstGeom><a:noFill/><a:ln cap="flat" cmpd="sng" w="9525"><a:solidFill><a:schemeClr val="dk2"/></a:solidFill><a:prstDash val="dot"/><a:round/><a:headEnd len="med" w="med" type="none"/><a:tailEnd len="med" w="med" type="none"/></a:ln></p:spPr></p:cxnSp><p:cxnSp><p:nvCxnSpPr><p:cNvPr id="421" name="Google Shape;421;p25"/><p:cNvCxnSpPr/><p:nvPr/></p:nvCxnSpPr><p:spPr><a:xfrm><a:off x="2665325" y="2275525"/><a:ext cx="3876900" cy="0"/></a:xfrm><a:prstGeom prst="straightConnector1"><a:avLst/></a:prstGeom><a:noFill/><a:ln cap="flat" cmpd="sng" w="9525"><a:solidFill><a:schemeClr val="dk2"/></a:solidFill><a:prstDash val="dot"/><a:round/><a:headEnd len="med" w="med" type="none"/><a:tailEnd len="med" w="med" type="none"/></a:ln></p:spPr></p:cxnSp><p:cxnSp><p:nvCxnSpPr><p:cNvPr id="422" name="Google Shape;422;p25"/><p:cNvCxnSpPr/><p:nvPr/></p:nvCxnSpPr><p:spPr><a:xfrm><a:off x="2665325" y="2503075"/><a:ext cx="3876900" cy="0"/></a:xfrm><a:prstGeom prst="straightConnector1"><a:avLst/></a:prstGeom><a:noFill/><a:ln cap="flat" cmpd="sng" w="9525"><a:solidFill><a:schemeClr val="dk2"/></a:solidFill><a:prstDash val="dot"/><a:round/><a:headEnd len="med" w="med" type="none"/><a:tailEnd len="med" w="med" type="none"/></a:ln></p:spPr></p:cxnSp><p:cxnSp><p:nvCxnSpPr><p:cNvPr id="423" name="Google Shape;423;p25"/><p:cNvCxnSpPr/><p:nvPr/></p:nvCxnSpPr><p:spPr><a:xfrm><a:off x="2665325" y="2730625"/><a:ext cx="3876900" cy="0"/></a:xfrm><a:prstGeom prst="straightConnector1"><a:avLst/></a:prstGeom><a:noFill/><a:ln cap="flat" cmpd="sng" w="9525"><a:solidFill><a:schemeClr val="dk2"/></a:solidFill><a:prstDash val="dot"/><a:round/><a:headEnd len="med" w="med" type="none"/><a:tailEnd len="med" w="med" type="none"/></a:ln></p:spPr></p:cxnSp><p:cxnSp><p:nvCxnSpPr><p:cNvPr id="424" name="Google Shape;424;p25"/><p:cNvCxnSpPr/><p:nvPr/></p:nvCxnSpPr><p:spPr><a:xfrm><a:off x="2665325" y="2958175"/><a:ext cx="3876900" cy="0"/></a:xfrm><a:prstGeom prst="straightConnector1"><a:avLst/></a:prstGeom><a:noFill/><a:ln cap="flat" cmpd="sng" w="9525"><a:solidFill><a:schemeClr val="dk2"/></a:solidFill><a:prstDash val="dot"/><a:round/><a:headEnd len="med" w="med" type="none"/><a:tailEnd len="med" w="med" type="none"/></a:ln></p:spPr></p:cxnSp><p:cxnSp><p:nvCxnSpPr><p:cNvPr id="425" name="Google Shape;425;p25"/><p:cNvCxnSpPr/><p:nvPr/></p:nvCxnSpPr><p:spPr><a:xfrm><a:off x="2665325" y="3185725"/><a:ext cx="3876900" cy="0"/></a:xfrm><a:prstGeom prst="straightConnector1"><a:avLst/></a:prstGeom><a:noFill/><a:ln cap="flat" cmpd="sng" w="9525"><a:solidFill><a:schemeClr val="dk2"/></a:solidFill><a:prstDash val="dot"/><a:round/><a:headEnd len="med" w="med" type="none"/><a:tailEnd len="med" w="med" type="none"/></a:ln></p:spPr></p:cxnSp><p:cxnSp><p:nvCxnSpPr><p:cNvPr id="426" name="Google Shape;426;p25"/><p:cNvCxnSpPr/><p:nvPr/></p:nvCxnSpPr><p:spPr><a:xfrm><a:off x="2665325" y="3413275"/><a:ext cx="3876900" cy="0"/></a:xfrm><a:prstGeom prst="straightConnector1"><a:avLst/></a:prstGeom><a:noFill/><a:ln cap="flat" cmpd="sng" w="9525"><a:solidFill><a:schemeClr val="dk2"/></a:solidFill><a:prstDash val="dot"/><a:round/><a:headEnd len="med" w="med" type="none"/><a:tailEnd len="med" w="med" type="none"/></a:ln></p:spPr></p:cxnSp></p:grpSp><p:sp><p:nvSpPr><p:cNvPr id="427" name="Google Shape;427;p25"/><p:cNvSpPr txBox="1"/><p:nvPr><p:ph type="title"/></p:nvPr></p:nvSpPr><p:spPr><a:xfrm><a:off x="457200" y="411475"/><a:ext cx="8229600" cy="481500"/></a:xfrm><a:prstGeom prst="rect"><a:avLst/></a:prstGeom></p:spPr><p:txBody><a:bodyPr anchorCtr="0" anchor="ctr" bIns="91425" lIns="91425" spcFirstLastPara="1" rIns="91425" wrap="square" tIns="91425"><a:noAutofit/></a:bodyPr><a:lstStyle/><a:p><a:pPr indent="0" lvl="0" marL="0" rtl="0" algn="ctr"><a:spcBef><a:spcPts val="0"/></a:spcBef><a:spcAft><a:spcPts val="0"/></a:spcAft><a:buNone/></a:pPr><a:r><a:rPr lang="en"><a:solidFill><a:schemeClr val="dk1"/></a:solidFill></a:rPr><a:t>Design Elements Infographics</a:t></a:r><a:endParaRPr><a:solidFill><a:schemeClr val="dk1"/></a:solidFill></a:endParaRPr></a:p></p:txBody></p:sp><p:sp><p:nvSpPr><p:cNvPr id="428" name="Google Shape;428;p25"/><p:cNvSpPr/><p:nvPr/></p:nvSpPr><p:spPr><a:xfrm><a:off x="-7662110" y="1348581"/><a:ext cx="6299225" cy="1213925"/></a:xfrm><a:custGeom><a:rect b="b" l="l" r="r" t="t"/><a:pathLst><a:path extrusionOk="0" h="48557" w="157520"><a:moveTo><a:pt x="0" y="48557"/></a:moveTo><a:cubicBezTo><a:pt x="9046" y="43490"/><a:pt x="37575" y="19993"/><a:pt x="54277" y="18157"/></a:cubicBezTo><a:cubicBezTo><a:pt x="70979" y="16321"/><a:pt x="87779" y="40421"/><a:pt x="100210" y="37541"/></a:cubicBezTo><a:cubicBezTo><a:pt x="112641" y="34662"/><a:pt x="119313" y="5234"/><a:pt x="128865" y="880"/></a:cubicBezTo><a:cubicBezTo><a:pt x="138417" y="-3474"/><a:pt x="152744" y="9659"/><a:pt x="157520" y="11415"/></a:cubicBezTo></a:path></a:pathLst></a:custGeom><a:noFill/><a:ln cap="flat" cmpd="sng" w="38100"><a:solidFill><a:schemeClr val="accent3"/></a:solidFill><a:prstDash val="solid"/><a:round/><a:headEnd len="med" w="med" type="none"/><a:tailEnd len="med" w="med" type="none"/></a:ln></p:spPr></p:sp><p:sp><p:nvSpPr><p:cNvPr id="429" name="Google Shape;429;p25"/><p:cNvSpPr/><p:nvPr/></p:nvSpPr><p:spPr><a:xfrm><a:off x="-7646787" y="1545731"/><a:ext cx="6205888" cy="890452"/></a:xfrm><a:custGeom><a:rect b="b" l="l" r="r" t="t"/><a:pathLst><a:path extrusionOk="0" h="38021" w="165656"><a:moveTo><a:pt x="0" y="16419"/></a:moveTo><a:cubicBezTo><a:pt x="11930" y="19964"/><a:pt x="51265" y="40348"/><a:pt x="71580" y="37689"/></a:cubicBezTo><a:cubicBezTo><a:pt x="91895" y="35030"/><a:pt x="106211" y="3671"/><a:pt x="121890" y="467"/></a:cubicBezTo><a:cubicBezTo><a:pt x="137569" y="-2737"/><a:pt x="158362" y="15465"/><a:pt x="165656" y="18464"/></a:cubicBezTo></a:path></a:pathLst></a:custGeom><a:noFill/><a:ln cap="flat" cmpd="sng" w="38100"><a:solidFill><a:schemeClr val="accent2"/></a:solidFill><a:prstDash val="solid"/><a:round/><a:headEnd len="med" w="med" type="none"/><a:tailEnd len="med" w="med" type="none"/></a:ln></p:spPr></p:sp><p:sp><p:nvSpPr><p:cNvPr id="430" name="Google Shape;430;p25"/><p:cNvSpPr/><p:nvPr/></p:nvSpPr><p:spPr><a:xfrm><a:off x="-7616160" y="2167329"/><a:ext cx="6190612" cy="1116125"/></a:xfrm><a:custGeom><a:rect b="b" l="l" r="r" t="t"/><a:pathLst><a:path extrusionOk="0" h="44645" w="154804"><a:moveTo><a:pt x="0" y="29219"/></a:moveTo><a:cubicBezTo><a:pt x="10540" y="24375"/><a:pt x="43892" y="-2271"/><a:pt x="63242" y="156"/></a:cubicBezTo><a:cubicBezTo><a:pt x="82593" y="2583"/><a:pt x="100843" y="38936"/><a:pt x="116103" y="43780"/></a:cubicBezTo><a:cubicBezTo><a:pt x="131363" y="48624"/><a:pt x="148354" y="31646"/><a:pt x="154804" y="29219"/></a:cubicBezTo></a:path></a:pathLst></a:custGeom><a:noFill/><a:ln cap="flat" cmpd="sng" w="38100"><a:solidFill><a:schemeClr val="accent5"/></a:solidFill><a:prstDash val="solid"/><a:round/><a:headEnd len="med" w="med" type="none"/><a:tailEnd len="med" w="med" type="none"/></a:ln></p:spPr></p:sp><p:sp><p:nvSpPr><p:cNvPr id="431" name="Google Shape;431;p25"/><p:cNvSpPr/><p:nvPr/></p:nvSpPr><p:spPr><a:xfrm><a:off x="-7631464" y="2409241"/><a:ext cx="6205888" cy="881318"/></a:xfrm><a:custGeom><a:rect b="b" l="l" r="r" t="t"/><a:pathLst><a:path extrusionOk="0" h="37631" w="165656"><a:moveTo><a:pt x="0" y="37631"/></a:moveTo><a:cubicBezTo><a:pt x="6749" y="34223"/><a:pt x="27746" y="17248"/><a:pt x="40494" y="17180"/></a:cubicBezTo><a:cubicBezTo><a:pt x="53242" y="17112"/><a:pt x="55628" y="40085"/><a:pt x="76488" y="37222"/></a:cubicBezTo><a:cubicBezTo><a:pt x="97348" y="34359"/><a:pt x="150795" y="6204"/><a:pt x="165656" y="0"/></a:cubicBezTo></a:path></a:pathLst></a:custGeom><a:noFill/><a:ln cap="flat" cmpd="sng" w="38100"><a:solidFill><a:schemeClr val="accent6"/></a:solidFill><a:prstDash val="solid"/><a:round/><a:headEnd len="med" w="med" type="none"/><a:tailEnd len="med" w="med" type="none"/></a:ln></p:spPr></p:sp><p:sp><p:nvSpPr><p:cNvPr id="432" name="Google Shape;432;p25"/><p:cNvSpPr txBox="1"/><p:nvPr/></p:nvSpPr><p:spPr><a:xfrm><a:off x="709050" y="3776969"/><a:ext cx="1900200" cy="327900"/></a:xfrm><a:prstGeom prst="rect"><a:avLst/></a:prstGeom><a:noFill/><a:ln><a:noFill/></a:ln></p:spPr><p:txBody><a:bodyPr anchorCtr="0" anchor="ctr" bIns="0" lIns="182875" spcFirstLastPara="1" rIns="182875" wrap="square" tIns="0"><a:noAutofit/></a:bodyPr><a:lstStyle/><a:p><a:pPr indent="0" lvl="0" marL="0" rtl="0" algn="ctr"><a:spcBef><a:spcPts val="0"/></a:spcBef><a:spcAft><a:spcPts val="0"/></a:spcAft><a:buNone/></a:pPr><a:r><a:rPr b="1" lang="en" sz="1600"><a:solidFill><a:schemeClr val="accent1"/></a:solidFill><a:latin typeface="Fira Sans Extra Condensed"/><a:ea typeface="Fira Sans Extra Condensed"/><a:cs typeface="Fira Sans Extra Condensed"/><a:sym typeface="Fira Sans Extra Condensed"/></a:rPr><a:t>Mercury</a:t></a:r><a:endParaRPr b="1" sz="1600"><a:solidFill><a:schemeClr val="accent1"/></a:solidFill><a:latin typeface="Fira Sans Extra Condensed"/><a:ea typeface="Fira Sans Extra Condensed"/><a:cs typeface="Fira Sans Extra Condensed"/><a:sym typeface="Fira Sans Extra Condensed"/></a:endParaRPr></a:p></p:txBody></p:sp><p:sp><p:nvSpPr><p:cNvPr id="433" name="Google Shape;433;p25"/><p:cNvSpPr txBox="1"/><p:nvPr/></p:nvSpPr><p:spPr><a:xfrm><a:off x="709050" y="4104875"/><a:ext cx="1900200" cy="752100"/></a:xfrm><a:prstGeom prst="rect"><a:avLst/></a:prstGeom><a:noFill/><a:ln><a:noFill/></a:ln></p:spPr><p:txBody><a:bodyPr anchorCtr="0" anchor="ctr" bIns="0" lIns="182875" spcFirstLastPara="1" rIns="182875" wrap="square" tIns="0"><a:noAutofit/></a:bodyPr><a:lstStyle/><a:p><a:pPr indent="0" lvl="0" marL="0" rtl="0" algn="ctr"><a:lnSpc><a:spcPct val="115000"/></a:lnSpc><a:spcBef><a:spcPts val="0"/></a:spcBef><a:spcAft><a:spcPts val="0"/></a:spcAft><a:buNone/></a:pPr><a:r><a:rPr lang="en" sz="1200"><a:solidFill><a:srgbClr val="000000"/></a:solidFill><a:latin typeface="Roboto"/><a:ea typeface="Roboto"/><a:cs typeface="Roboto"/><a:sym typeface="Roboto"/></a:rPr><a:t>Mercury is the closest planet to the Sun and the smallest one</a:t></a:r><a:endParaRPr sz="1200"><a:latin typeface="Roboto"/><a:ea typeface="Roboto"/><a:cs typeface="Roboto"/><a:sym typeface="Roboto"/></a:endParaRPr></a:p></p:txBody></p:sp><p:sp><p:nvSpPr><p:cNvPr id="434" name="Google Shape;434;p25"/><p:cNvSpPr txBox="1"/><p:nvPr/></p:nvSpPr><p:spPr><a:xfrm><a:off x="2650950" y="3776969"/><a:ext cx="1900200" cy="327900"/></a:xfrm><a:prstGeom prst="rect"><a:avLst/></a:prstGeom><a:noFill/><a:ln><a:noFill/></a:ln></p:spPr><p:txBody><a:bodyPr anchorCtr="0" anchor="ctr" bIns="0" lIns="182875" spcFirstLastPara="1" rIns="182875" wrap="square" tIns="0"><a:noAutofit/></a:bodyPr><a:lstStyle/><a:p><a:pPr indent="0" lvl="0" marL="0" rtl="0" algn="ctr"><a:spcBef><a:spcPts val="0"/></a:spcBef><a:spcAft><a:spcPts val="0"/></a:spcAft><a:buNone/></a:pPr><a:r><a:rPr b="1" lang="en" sz="1600"><a:solidFill><a:schemeClr val="accent2"/></a:solidFill><a:latin typeface="Fira Sans Extra Condensed"/><a:ea typeface="Fira Sans Extra Condensed"/><a:cs typeface="Fira Sans Extra Condensed"/><a:sym typeface="Fira Sans Extra Condensed"/></a:rPr><a:t>Mars</a:t></a:r><a:endParaRPr b="1" sz="1600"><a:solidFill><a:schemeClr val="accent2"/></a:solidFill><a:latin typeface="Fira Sans Extra Condensed"/><a:ea typeface="Fira Sans Extra Condensed"/><a:cs typeface="Fira Sans Extra Condensed"/><a:sym typeface="Fira Sans Extra Condensed"/></a:endParaRPr></a:p></p:txBody></p:sp><p:sp><p:nvSpPr><p:cNvPr id="435" name="Google Shape;435;p25"/><p:cNvSpPr txBox="1"/><p:nvPr/></p:nvSpPr><p:spPr><a:xfrm><a:off x="2650950" y="4104875"/><a:ext cx="1900200" cy="752100"/></a:xfrm><a:prstGeom prst="rect"><a:avLst/></a:prstGeom><a:noFill/><a:ln><a:noFill/></a:ln></p:spPr><p:txBody><a:bodyPr anchorCtr="0" anchor="ctr" bIns="0" lIns="182875" spcFirstLastPara="1" rIns="182875" wrap="square" tIns="0"><a:noAutofit/></a:bodyPr><a:lstStyle/><a:p><a:pPr indent="0" lvl="0" marL="0" rtl="0" algn="ctr"><a:lnSpc><a:spcPct val="115000"/></a:lnSpc><a:spcBef><a:spcPts val="0"/></a:spcBef><a:spcAft><a:spcPts val="0"/></a:spcAft><a:buNone/></a:pPr><a:r><a:rPr lang="en" sz="1200"><a:solidFill><a:srgbClr val="000000"/></a:solidFill><a:latin typeface="Roboto"/><a:ea typeface="Roboto"/><a:cs typeface="Roboto"/><a:sym typeface="Roboto"/></a:rPr><a:t>Despite being red, it</a:t></a:r><a:r><a:rPr lang="en" sz="1200"><a:latin typeface="Roboto"/><a:ea typeface="Roboto"/><a:cs typeface="Roboto"/><a:sym typeface="Roboto"/></a:rPr><a:t>’</a:t></a:r><a:r><a:rPr lang="en" sz="1200"><a:solidFill><a:srgbClr val="000000"/></a:solidFill><a:latin typeface="Roboto"/><a:ea typeface="Roboto"/><a:cs typeface="Roboto"/><a:sym typeface="Roboto"/></a:rPr><a:t>s a cold place full of iron oxide dust</a:t></a:r><a:endParaRPr sz="1200"><a:solidFill><a:srgbClr val="000000"/></a:solidFill><a:latin typeface="Roboto"/><a:ea typeface="Roboto"/><a:cs typeface="Roboto"/><a:sym typeface="Roboto"/></a:endParaRPr></a:p></p:txBody></p:sp><p:sp><p:nvSpPr><p:cNvPr id="436" name="Google Shape;436;p25"/><p:cNvSpPr txBox="1"/><p:nvPr/></p:nvSpPr><p:spPr><a:xfrm><a:off x="4592850" y="3776969"/><a:ext cx="1900200" cy="327900"/></a:xfrm><a:prstGeom prst="rect"><a:avLst/></a:prstGeom><a:noFill/><a:ln><a:noFill/></a:ln></p:spPr><p:txBody><a:bodyPr anchorCtr="0" anchor="ctr" bIns="0" lIns="182875" spcFirstLastPara="1" rIns="182875" wrap="square" tIns="0"><a:noAutofit/></a:bodyPr><a:lstStyle/><a:p><a:pPr indent="0" lvl="0" marL="0" rtl="0" algn="ctr"><a:spcBef><a:spcPts val="0"/></a:spcBef><a:spcAft><a:spcPts val="0"/></a:spcAft><a:buNone/></a:pPr><a:r><a:rPr b="1" lang="en" sz="1600"><a:solidFill><a:schemeClr val="accent4"/></a:solidFill><a:latin typeface="Fira Sans Extra Condensed"/><a:ea typeface="Fira Sans Extra Condensed"/><a:cs typeface="Fira Sans Extra Condensed"/><a:sym typeface="Fira Sans Extra Condensed"/></a:rPr><a:t>Jupiter</a:t></a:r><a:endParaRPr b="1" sz="1600"><a:solidFill><a:schemeClr val="accent4"/></a:solidFill><a:latin typeface="Fira Sans Extra Condensed"/><a:ea typeface="Fira Sans Extra Condensed"/><a:cs typeface="Fira Sans Extra Condensed"/><a:sym typeface="Fira Sans Extra Condensed"/></a:endParaRPr></a:p></p:txBody></p:sp><p:sp><p:nvSpPr><p:cNvPr id="437" name="Google Shape;437;p25"/><p:cNvSpPr txBox="1"/><p:nvPr/></p:nvSpPr><p:spPr><a:xfrm><a:off x="4592850" y="4104875"/><a:ext cx="1900200" cy="752100"/></a:xfrm><a:prstGeom prst="rect"><a:avLst/></a:prstGeom><a:noFill/><a:ln><a:noFill/></a:ln></p:spPr><p:txBody><a:bodyPr anchorCtr="0" anchor="ctr" bIns="0" lIns="182875" spcFirstLastPara="1" rIns="182875" wrap="square" tIns="0"><a:noAutofit/></a:bodyPr><a:lstStyle/><a:p><a:pPr indent="0" lvl="0" marL="0" rtl="0" algn="ctr"><a:lnSpc><a:spcPct val="115000"/></a:lnSpc><a:spcBef><a:spcPts val="0"/></a:spcBef><a:spcAft><a:spcPts val="0"/></a:spcAft><a:buNone/></a:pPr><a:r><a:rPr lang="en" sz="1200"><a:solidFill><a:srgbClr val="000000"/></a:solidFill><a:latin typeface="Roboto"/><a:ea typeface="Roboto"/><a:cs typeface="Roboto"/><a:sym typeface="Roboto"/></a:rPr><a:t>It’s a gas giant and the biggest planet in the Solar System</a:t></a:r><a:endParaRPr sz="1200"><a:solidFill><a:srgbClr val="000000"/></a:solidFill><a:latin typeface="Roboto"/><a:ea typeface="Roboto"/><a:cs typeface="Roboto"/><a:sym typeface="Roboto"/></a:endParaRPr></a:p></p:txBody></p:sp><p:sp><p:nvSpPr><p:cNvPr id="438" name="Google Shape;438;p25"/><p:cNvSpPr txBox="1"/><p:nvPr/></p:nvSpPr><p:spPr><a:xfrm><a:off x="6534750" y="3776969"/><a:ext cx="1900200" cy="327900"/></a:xfrm><a:prstGeom prst="rect"><a:avLst/></a:prstGeom><a:noFill/><a:ln><a:noFill/></a:ln></p:spPr><p:txBody><a:bodyPr anchorCtr="0" anchor="ctr" bIns="0" lIns="182875" spcFirstLastPara="1" rIns="182875" wrap="square" tIns="0"><a:noAutofit/></a:bodyPr><a:lstStyle/><a:p><a:pPr indent="0" lvl="0" marL="0" rtl="0" algn="ctr"><a:spcBef><a:spcPts val="0"/></a:spcBef><a:spcAft><a:spcPts val="0"/></a:spcAft><a:buNone/></a:pPr><a:r><a:rPr b="1" lang="en" sz="1600"><a:solidFill><a:schemeClr val="accent6"/></a:solidFill><a:latin typeface="Fira Sans Extra Condensed"/><a:ea typeface="Fira Sans Extra Condensed"/><a:cs typeface="Fira Sans Extra Condensed"/><a:sym typeface="Fira Sans Extra Condensed"/></a:rPr><a:t>Mercury</a:t></a:r><a:endParaRPr b="1" sz="1600"><a:solidFill><a:schemeClr val="accent6"/></a:solidFill><a:latin typeface="Fira Sans Extra Condensed"/><a:ea typeface="Fira Sans Extra Condensed"/><a:cs typeface="Fira Sans Extra Condensed"/><a:sym typeface="Fira Sans Extra Condensed"/></a:endParaRPr></a:p></p:txBody></p:sp><p:sp><p:nvSpPr><p:cNvPr id="439" name="Google Shape;439;p25"/><p:cNvSpPr txBox="1"/><p:nvPr/></p:nvSpPr><p:spPr><a:xfrm><a:off x="6534750" y="4104875"/><a:ext cx="1900200" cy="752100"/></a:xfrm><a:prstGeom prst="rect"><a:avLst/></a:prstGeom><a:noFill/><a:ln><a:noFill/></a:ln></p:spPr><p:txBody><a:bodyPr anchorCtr="0" anchor="ctr" bIns="0" lIns="182875" spcFirstLastPara="1" rIns="182875" wrap="square" tIns="0"><a:noAutofit/></a:bodyPr><a:lstStyle/><a:p><a:pPr indent="0" lvl="0" marL="0" rtl="0" algn="ctr"><a:lnSpc><a:spcPct val="115000"/></a:lnSpc><a:spcBef><a:spcPts val="0"/></a:spcBef><a:spcAft><a:spcPts val="0"/></a:spcAft><a:buNone/></a:pPr><a:r><a:rPr lang="en" sz="1200"><a:solidFill><a:srgbClr val="000000"/></a:solidFill><a:latin typeface="Roboto"/><a:ea typeface="Roboto"/><a:cs typeface="Roboto"/><a:sym typeface="Roboto"/></a:rPr><a:t>Mercury is the closest planet to the Sun and the smallest one</a:t></a:r><a:endParaRPr sz="1200"><a:latin typeface="Roboto"/><a:ea typeface="Roboto"/><a:cs typeface="Roboto"/><a:sym typeface="Roboto"/></a:endParaRPr></a:p></p:txBody></p:sp><p:sp><p:nvSpPr><p:cNvPr id="440" name="Google Shape;440;p25"/><p:cNvSpPr txBox="1"/><p:nvPr/></p:nvSpPr><p:spPr><a:xfrm><a:off x="-865875" y="1085338"/><a:ext cx="448500" cy="216600"/></a:xfrm><a:prstGeom prst="rect"><a:avLst/></a:prstGeom><a:noFill/><a:ln><a:noFill/></a:ln></p:spPr><p:txBody><a:bodyPr anchorCtr="0" anchor="ctr" bIns="91425" lIns="91425" spcFirstLastPara="1" rIns="91425" wrap="square" tIns="91425"><a:noAutofit/></a:bodyPr><a:lstStyle/><a:p><a:pPr indent="0" lvl="0" marL="0" rtl="0" algn="l"><a:spcBef><a:spcPts val="0"/></a:spcBef><a:spcAft><a:spcPts val="0"/></a:spcAft><a:buNone/></a:pPr><a:r><a:rPr lang="en" sz="1200"><a:latin typeface="Roboto"/><a:ea typeface="Roboto"/><a:cs typeface="Roboto"/><a:sym typeface="Roboto"/></a:rPr><a:t>100</a:t></a:r><a:endParaRPr sz="1200"><a:latin typeface="Roboto"/><a:ea typeface="Roboto"/><a:cs typeface="Roboto"/><a:sym typeface="Roboto"/></a:endParaRPr></a:p></p:txBody></p:sp><p:sp><p:nvSpPr><p:cNvPr id="441" name="Google Shape;441;p25"/><p:cNvSpPr txBox="1"/><p:nvPr/></p:nvSpPr><p:spPr><a:xfrm><a:off x="-865875" y="1315913"/><a:ext cx="448500" cy="216600"/></a:xfrm><a:prstGeom prst="rect"><a:avLst/></a:prstGeom><a:noFill/><a:ln><a:noFill/></a:ln></p:spPr><p:txBody><a:bodyPr anchorCtr="0" anchor="ctr" bIns="91425" lIns="91425" spcFirstLastPara="1" rIns="91425" wrap="square" tIns="91425"><a:noAutofit/></a:bodyPr><a:lstStyle/><a:p><a:pPr indent="0" lvl="0" marL="0" rtl="0" algn="l"><a:spcBef><a:spcPts val="0"/></a:spcBef><a:spcAft><a:spcPts val="0"/></a:spcAft><a:buNone/></a:pPr><a:r><a:rPr lang="en" sz="1200"><a:latin typeface="Roboto"/><a:ea typeface="Roboto"/><a:cs typeface="Roboto"/><a:sym typeface="Roboto"/></a:rPr><a:t>90</a:t></a:r><a:endParaRPr sz="1200"><a:latin typeface="Roboto"/><a:ea typeface="Roboto"/><a:cs typeface="Roboto"/><a:sym typeface="Roboto"/></a:endParaRPr></a:p></p:txBody></p:sp><p:sp><p:nvSpPr><p:cNvPr id="442" name="Google Shape;442;p25"/><p:cNvSpPr txBox="1"/><p:nvPr/></p:nvSpPr><p:spPr><a:xfrm><a:off x="-865875" y="1546488"/><a:ext cx="448500" cy="216600"/></a:xfrm><a:prstGeom prst="rect"><a:avLst/></a:prstGeom><a:noFill/><a:ln><a:noFill/></a:ln></p:spPr><p:txBody><a:bodyPr anchorCtr="0" anchor="ctr" bIns="91425" lIns="91425" spcFirstLastPara="1" rIns="91425" wrap="square" tIns="91425"><a:noAutofit/></a:bodyPr><a:lstStyle/><a:p><a:pPr indent="0" lvl="0" marL="0" rtl="0" algn="l"><a:spcBef><a:spcPts val="0"/></a:spcBef><a:spcAft><a:spcPts val="0"/></a:spcAft><a:buNone/></a:pPr><a:r><a:rPr lang="en" sz="1200"><a:latin typeface="Roboto"/><a:ea typeface="Roboto"/><a:cs typeface="Roboto"/><a:sym typeface="Roboto"/></a:rPr><a:t>80</a:t></a:r><a:endParaRPr sz="1200"><a:latin typeface="Roboto"/><a:ea typeface="Roboto"/><a:cs typeface="Roboto"/><a:sym typeface="Roboto"/></a:endParaRPr></a:p></p:txBody></p:sp><p:sp><p:nvSpPr><p:cNvPr id="443" name="Google Shape;443;p25"/><p:cNvSpPr txBox="1"/><p:nvPr/></p:nvSpPr><p:spPr><a:xfrm><a:off x="-865875" y="1777063"/><a:ext cx="448500" cy="216600"/></a:xfrm><a:prstGeom prst="rect"><a:avLst/></a:prstGeom><a:noFill/><a:ln><a:noFill/></a:ln></p:spPr><p:txBody><a:bodyPr anchorCtr="0" anchor="ctr" bIns="91425" lIns="91425" spcFirstLastPara="1" rIns="91425" wrap="square" tIns="91425"><a:noAutofit/></a:bodyPr><a:lstStyle/><a:p><a:pPr indent="0" lvl="0" marL="0" rtl="0" algn="l"><a:spcBef><a:spcPts val="0"/></a:spcBef><a:spcAft><a:spcPts val="0"/></a:spcAft><a:buNone/></a:pPr><a:r><a:rPr lang="en" sz="1200"><a:latin typeface="Roboto"/><a:ea typeface="Roboto"/><a:cs typeface="Roboto"/><a:sym typeface="Roboto"/></a:rPr><a:t>70</a:t></a:r><a:endParaRPr sz="1200"><a:latin typeface="Roboto"/><a:ea typeface="Roboto"/><a:cs typeface="Roboto"/><a:sym typeface="Roboto"/></a:endParaRPr></a:p></p:txBody></p:sp><p:sp><p:nvSpPr><p:cNvPr id="444" name="Google Shape;444;p25"/><p:cNvSpPr txBox="1"/><p:nvPr/></p:nvSpPr><p:spPr><a:xfrm><a:off x="-865875" y="2007638"/><a:ext cx="448500" cy="216600"/></a:xfrm><a:prstGeom prst="rect"><a:avLst/></a:prstGeom><a:noFill/><a:ln><a:noFill/></a:ln></p:spPr><p:txBody><a:bodyPr anchorCtr="0" anchor="ctr" bIns="91425" lIns="91425" spcFirstLastPara="1" rIns="91425" wrap="square" tIns="91425"><a:noAutofit/></a:bodyPr><a:lstStyle/><a:p><a:pPr indent="0" lvl="0" marL="0" rtl="0" algn="l"><a:spcBef><a:spcPts val="0"/></a:spcBef><a:spcAft><a:spcPts val="0"/></a:spcAft><a:buNone/></a:pPr><a:r><a:rPr lang="en" sz="1200"><a:latin typeface="Roboto"/><a:ea typeface="Roboto"/><a:cs typeface="Roboto"/><a:sym typeface="Roboto"/></a:rPr><a:t>60</a:t></a:r><a:endParaRPr sz="1200"><a:latin typeface="Roboto"/><a:ea typeface="Roboto"/><a:cs typeface="Roboto"/><a:sym typeface="Roboto"/></a:endParaRPr></a:p></p:txBody></p:sp><p:sp><p:nvSpPr><p:cNvPr id="445" name="Google Shape;445;p25"/><p:cNvSpPr txBox="1"/><p:nvPr/></p:nvSpPr><p:spPr><a:xfrm><a:off x="-865875" y="2238213"/><a:ext cx="448500" cy="216600"/></a:xfrm><a:prstGeom prst="rect"><a:avLst/></a:prstGeom><a:noFill/><a:ln><a:noFill/></a:ln></p:spPr><p:txBody><a:bodyPr anchorCtr="0" anchor="ctr" bIns="91425" lIns="91425" spcFirstLastPara="1" rIns="91425" wrap="square" tIns="91425"><a:noAutofit/></a:bodyPr><a:lstStyle/><a:p><a:pPr indent="0" lvl="0" marL="0" rtl="0" algn="l"><a:spcBef><a:spcPts val="0"/></a:spcBef><a:spcAft><a:spcPts val="0"/></a:spcAft><a:buNone/></a:pPr><a:r><a:rPr lang="en" sz="1200"><a:latin typeface="Roboto"/><a:ea typeface="Roboto"/><a:cs typeface="Roboto"/><a:sym typeface="Roboto"/></a:rPr><a:t>50</a:t></a:r><a:endParaRPr sz="1200"><a:latin typeface="Roboto"/><a:ea typeface="Roboto"/><a:cs typeface="Roboto"/><a:sym typeface="Roboto"/></a:endParaRPr></a:p></p:txBody></p:sp><p:sp><p:nvSpPr><p:cNvPr id="446" name="Google Shape;446;p25"/><p:cNvSpPr txBox="1"/><p:nvPr/></p:nvSpPr><p:spPr><a:xfrm><a:off x="-865875" y="2468788"/><a:ext cx="448500" cy="216600"/></a:xfrm><a:prstGeom prst="rect"><a:avLst/></a:prstGeom><a:noFill/><a:ln><a:noFill/></a:ln></p:spPr><p:txBody><a:bodyPr anchorCtr="0" anchor="ctr" bIns="91425" lIns="91425" spcFirstLastPara="1" rIns="91425" wrap="square" tIns="91425"><a:noAutofit/></a:bodyPr><a:lstStyle/><a:p><a:pPr indent="0" lvl="0" marL="0" rtl="0" algn="l"><a:spcBef><a:spcPts val="0"/></a:spcBef><a:spcAft><a:spcPts val="0"/></a:spcAft><a:buNone/></a:pPr><a:r><a:rPr lang="en" sz="1200"><a:latin typeface="Roboto"/><a:ea typeface="Roboto"/><a:cs typeface="Roboto"/><a:sym typeface="Roboto"/></a:rPr><a:t>40</a:t></a:r><a:endParaRPr sz="1200"><a:latin typeface="Roboto"/><a:ea typeface="Roboto"/><a:cs typeface="Roboto"/><a:sym typeface="Roboto"/></a:endParaRPr></a:p></p:txBody></p:sp><p:sp><p:nvSpPr><p:cNvPr id="447" name="Google Shape;447;p25"/><p:cNvSpPr txBox="1"/><p:nvPr/></p:nvSpPr><p:spPr><a:xfrm><a:off x="-865875" y="2699363"/><a:ext cx="448500" cy="216600"/></a:xfrm><a:prstGeom prst="rect"><a:avLst/></a:prstGeom><a:noFill/><a:ln><a:noFill/></a:ln></p:spPr><p:txBody><a:bodyPr anchorCtr="0" anchor="ctr" bIns="91425" lIns="91425" spcFirstLastPara="1" rIns="91425" wrap="square" tIns="91425"><a:noAutofit/></a:bodyPr><a:lstStyle/><a:p><a:pPr indent="0" lvl="0" marL="0" rtl="0" algn="l"><a:spcBef><a:spcPts val="0"/></a:spcBef><a:spcAft><a:spcPts val="0"/></a:spcAft><a:buNone/></a:pPr><a:r><a:rPr lang="en" sz="1200"><a:latin typeface="Roboto"/><a:ea typeface="Roboto"/><a:cs typeface="Roboto"/><a:sym typeface="Roboto"/></a:rPr><a:t>30</a:t></a:r><a:endParaRPr sz="1200"><a:latin typeface="Roboto"/><a:ea typeface="Roboto"/><a:cs typeface="Roboto"/><a:sym typeface="Roboto"/></a:endParaRPr></a:p></p:txBody></p:sp><p:sp><p:nvSpPr><p:cNvPr id="448" name="Google Shape;448;p25"/><p:cNvSpPr txBox="1"/><p:nvPr/></p:nvSpPr><p:spPr><a:xfrm><a:off x="-865875" y="2929938"/><a:ext cx="448500" cy="216600"/></a:xfrm><a:prstGeom prst="rect"><a:avLst/></a:prstGeom><a:noFill/><a:ln><a:noFill/></a:ln></p:spPr><p:txBody><a:bodyPr anchorCtr="0" anchor="ctr" bIns="91425" lIns="91425" spcFirstLastPara="1" rIns="91425" wrap="square" tIns="91425"><a:noAutofit/></a:bodyPr><a:lstStyle/><a:p><a:pPr indent="0" lvl="0" marL="0" rtl="0" algn="l"><a:spcBef><a:spcPts val="0"/></a:spcBef><a:spcAft><a:spcPts val="0"/></a:spcAft><a:buNone/></a:pPr><a:r><a:rPr lang="en" sz="1200"><a:latin typeface="Roboto"/><a:ea typeface="Roboto"/><a:cs typeface="Roboto"/><a:sym typeface="Roboto"/></a:rPr><a:t>20</a:t></a:r><a:endParaRPr sz="1200"><a:latin typeface="Roboto"/><a:ea typeface="Roboto"/><a:cs typeface="Roboto"/><a:sym typeface="Roboto"/></a:endParaRPr></a:p></p:txBody></p:sp><p:sp><p:nvSpPr><p:cNvPr id="449" name="Google Shape;449;p25"/><p:cNvSpPr txBox="1"/><p:nvPr/></p:nvSpPr><p:spPr><a:xfrm><a:off x="-865875" y="3160513"/><a:ext cx="448500" cy="216600"/></a:xfrm><a:prstGeom prst="rect"><a:avLst/></a:prstGeom><a:noFill/><a:ln><a:noFill/></a:ln></p:spPr><p:txBody><a:bodyPr anchorCtr="0" anchor="ctr" bIns="91425" lIns="91425" spcFirstLastPara="1" rIns="91425" wrap="square" tIns="91425"><a:noAutofit/></a:bodyPr><a:lstStyle/><a:p><a:pPr indent="0" lvl="0" marL="0" rtl="0" algn="l"><a:spcBef><a:spcPts val="0"/></a:spcBef><a:spcAft><a:spcPts val="0"/></a:spcAft><a:buNone/></a:pPr><a:r><a:rPr lang="en" sz="1200"><a:latin typeface="Roboto"/><a:ea typeface="Roboto"/><a:cs typeface="Roboto"/><a:sym typeface="Roboto"/></a:rPr><a:t>10</a:t></a:r><a:endParaRPr sz="1200"><a:latin typeface="Roboto"/><a:ea typeface="Roboto"/><a:cs typeface="Roboto"/><a:sym typeface="Roboto"/></a:endParaRPr></a:p></p:txBody></p:sp><p:sp><p:nvSpPr><p:cNvPr id="450" name="Google Shape;450;p25"/><p:cNvSpPr txBox="1"/><p:nvPr/></p:nvSpPr><p:spPr><a:xfrm><a:off x="-865875" y="3391088"/><a:ext cx="448500" cy="216600"/></a:xfrm><a:prstGeom prst="rect"><a:avLst/></a:prstGeom><a:noFill/><a:ln><a:noFill/></a:ln></p:spPr><p:txBody><a:bodyPr anchorCtr="0" anchor="ctr" bIns="91425" lIns="91425" spcFirstLastPara="1" rIns="91425" wrap="square" tIns="91425"><a:noAutofit/></a:bodyPr><a:lstStyle/><a:p><a:pPr indent="0" lvl="0" marL="0" rtl="0" algn="l"><a:spcBef><a:spcPts val="0"/></a:spcBef><a:spcAft><a:spcPts val="0"/></a:spcAft><a:buNone/></a:pPr><a:r><a:rPr lang="en" sz="1200"><a:latin typeface="Roboto"/><a:ea typeface="Roboto"/><a:cs typeface="Roboto"/><a:sym typeface="Roboto"/></a:rPr><a:t>0</a:t></a:r><a:endParaRPr sz="1200"><a:latin typeface="Roboto"/><a:ea typeface="Roboto"/><a:cs typeface="Roboto"/><a:sym typeface="Roboto"/></a:endParaRPr></a:p></p:txBody></p:sp><p:sp><p:nvSpPr><p:cNvPr id="451" name="Google Shape;451;p25"/><p:cNvSpPr txBox="1"/><p:nvPr/></p:nvSpPr><p:spPr><a:xfrm><a:off x="8315250" y="1176925"/><a:ext cx="371700" cy="216600"/></a:xfrm><a:prstGeom prst="rect"><a:avLst/></a:prstGeom><a:noFill/><a:ln><a:noFill/></a:ln></p:spPr><p:txBody><a:bodyPr anchorCtr="0" anchor="ctr" bIns="91425" lIns="91425" spcFirstLastPara="1" rIns="91425" wrap="square" tIns="91425"><a:noAutofit/></a:bodyPr><a:lstStyle/><a:p><a:pPr indent="0" lvl="0" marL="0" rtl="0" algn="l"><a:spcBef><a:spcPts val="0"/></a:spcBef><a:spcAft><a:spcPts val="0"/></a:spcAft><a:buNone/></a:pPr><a:r><a:rPr lang="en" sz="1200"><a:latin typeface="Roboto"/><a:ea typeface="Roboto"/><a:cs typeface="Roboto"/><a:sym typeface="Roboto"/></a:rPr><a:t>70</a:t></a:r><a:endParaRPr sz="1200"><a:latin typeface="Roboto"/><a:ea typeface="Roboto"/><a:cs typeface="Roboto"/><a:sym typeface="Roboto"/></a:endParaRPr></a:p></p:txBody></p:sp><p:sp><p:nvSpPr><p:cNvPr id="452" name="Google Shape;452;p25"/><p:cNvSpPr txBox="1"/><p:nvPr/></p:nvSpPr><p:spPr><a:xfrm><a:off x="8315250" y="1524179"/><a:ext cx="371700" cy="216600"/></a:xfrm><a:prstGeom prst="rect"><a:avLst/></a:prstGeom><a:noFill/><a:ln><a:noFill/></a:ln></p:spPr><p:txBody><a:bodyPr anchorCtr="0" anchor="ctr" bIns="91425" lIns="91425" spcFirstLastPara="1" rIns="91425" wrap="square" tIns="91425"><a:noAutofit/></a:bodyPr><a:lstStyle/><a:p><a:pPr indent="0" lvl="0" marL="0" rtl="0" algn="l"><a:spcBef><a:spcPts val="0"/></a:spcBef><a:spcAft><a:spcPts val="0"/></a:spcAft><a:buNone/></a:pPr><a:r><a:rPr lang="en" sz="1200"><a:latin typeface="Roboto"/><a:ea typeface="Roboto"/><a:cs typeface="Roboto"/><a:sym typeface="Roboto"/></a:rPr><a:t>60</a:t></a:r><a:endParaRPr sz="1200"><a:latin typeface="Roboto"/><a:ea typeface="Roboto"/><a:cs typeface="Roboto"/><a:sym typeface="Roboto"/></a:endParaRPr></a:p></p:txBody></p:sp><p:sp><p:nvSpPr><p:cNvPr id="453" name="Google Shape;453;p25"/><p:cNvSpPr txBox="1"/><p:nvPr/></p:nvSpPr><p:spPr><a:xfrm><a:off x="8315250" y="1871432"/><a:ext cx="371700" cy="216600"/></a:xfrm><a:prstGeom prst="rect"><a:avLst/></a:prstGeom><a:noFill/><a:ln><a:noFill/></a:ln></p:spPr><p:txBody><a:bodyPr anchorCtr="0" anchor="ctr" bIns="91425" lIns="91425" spcFirstLastPara="1" rIns="91425" wrap="square" tIns="91425"><a:noAutofit/></a:bodyPr><a:lstStyle/><a:p><a:pPr indent="0" lvl="0" marL="0" rtl="0" algn="l"><a:spcBef><a:spcPts val="0"/></a:spcBef><a:spcAft><a:spcPts val="0"/></a:spcAft><a:buNone/></a:pPr><a:r><a:rPr lang="en" sz="1200"><a:latin typeface="Roboto"/><a:ea typeface="Roboto"/><a:cs typeface="Roboto"/><a:sym typeface="Roboto"/></a:rPr><a:t>50</a:t></a:r><a:endParaRPr sz="1200"><a:latin typeface="Roboto"/><a:ea typeface="Roboto"/><a:cs typeface="Roboto"/><a:sym typeface="Roboto"/></a:endParaRPr></a:p></p:txBody></p:sp><p:sp><p:nvSpPr><p:cNvPr id="454" name="Google Shape;454;p25"/><p:cNvSpPr txBox="1"/><p:nvPr/></p:nvSpPr><p:spPr><a:xfrm><a:off x="8315250" y="2218686"/><a:ext cx="371700" cy="216600"/></a:xfrm><a:prstGeom prst="rect"><a:avLst/></a:prstGeom><a:noFill/><a:ln><a:noFill/></a:ln></p:spPr><p:txBody><a:bodyPr anchorCtr="0" anchor="ctr" bIns="91425" lIns="91425" spcFirstLastPara="1" rIns="91425" wrap="square" tIns="91425"><a:noAutofit/></a:bodyPr><a:lstStyle/><a:p><a:pPr indent="0" lvl="0" marL="0" rtl="0" algn="l"><a:spcBef><a:spcPts val="0"/></a:spcBef><a:spcAft><a:spcPts val="0"/></a:spcAft><a:buNone/></a:pPr><a:r><a:rPr lang="en" sz="1200"><a:latin typeface="Roboto"/><a:ea typeface="Roboto"/><a:cs typeface="Roboto"/><a:sym typeface="Roboto"/></a:rPr><a:t>40</a:t></a:r><a:endParaRPr sz="1200"><a:latin typeface="Roboto"/><a:ea typeface="Roboto"/><a:cs typeface="Roboto"/><a:sym typeface="Roboto"/></a:endParaRPr></a:p></p:txBody></p:sp><p:sp><p:nvSpPr><p:cNvPr id="455" name="Google Shape;455;p25"/><p:cNvSpPr txBox="1"/><p:nvPr/></p:nvSpPr><p:spPr><a:xfrm><a:off x="8315250" y="2565939"/><a:ext cx="371700" cy="216600"/></a:xfrm><a:prstGeom prst="rect"><a:avLst/></a:prstGeom><a:noFill/><a:ln><a:noFill/></a:ln></p:spPr><p:txBody><a:bodyPr anchorCtr="0" anchor="ctr" bIns="91425" lIns="91425" spcFirstLastPara="1" rIns="91425" wrap="square" tIns="91425"><a:noAutofit/></a:bodyPr><a:lstStyle/><a:p><a:pPr indent="0" lvl="0" marL="0" rtl="0" algn="l"><a:spcBef><a:spcPts val="0"/></a:spcBef><a:spcAft><a:spcPts val="0"/></a:spcAft><a:buNone/></a:pPr><a:r><a:rPr lang="en" sz="1200"><a:latin typeface="Roboto"/><a:ea typeface="Roboto"/><a:cs typeface="Roboto"/><a:sym typeface="Roboto"/></a:rPr><a:t>30</a:t></a:r><a:endParaRPr sz="1200"><a:latin typeface="Roboto"/><a:ea typeface="Roboto"/><a:cs typeface="Roboto"/><a:sym typeface="Roboto"/></a:endParaRPr></a:p></p:txBody></p:sp><p:sp><p:nvSpPr><p:cNvPr id="456" name="Google Shape;456;p25"/><p:cNvSpPr txBox="1"/><p:nvPr/></p:nvSpPr><p:spPr><a:xfrm><a:off x="8315250" y="2913193"/><a:ext cx="371700" cy="216600"/></a:xfrm><a:prstGeom prst="rect"><a:avLst/></a:prstGeom><a:noFill/><a:ln><a:noFill/></a:ln></p:spPr><p:txBody><a:bodyPr anchorCtr="0" anchor="ctr" bIns="91425" lIns="91425" spcFirstLastPara="1" rIns="91425" wrap="square" tIns="91425"><a:noAutofit/></a:bodyPr><a:lstStyle/><a:p><a:pPr indent="0" lvl="0" marL="0" rtl="0" algn="l"><a:spcBef><a:spcPts val="0"/></a:spcBef><a:spcAft><a:spcPts val="0"/></a:spcAft><a:buNone/></a:pPr><a:r><a:rPr lang="en" sz="1200"><a:latin typeface="Roboto"/><a:ea typeface="Roboto"/><a:cs typeface="Roboto"/><a:sym typeface="Roboto"/></a:rPr><a:t>20</a:t></a:r><a:endParaRPr sz="1200"><a:latin typeface="Roboto"/><a:ea typeface="Roboto"/><a:cs typeface="Roboto"/><a:sym typeface="Roboto"/></a:endParaRPr></a:p></p:txBody></p:sp><p:sp><p:nvSpPr><p:cNvPr id="457" name="Google Shape;457;p25"/><p:cNvSpPr txBox="1"/><p:nvPr/></p:nvSpPr><p:spPr><a:xfrm><a:off x="8315250" y="3260446"/><a:ext cx="371700" cy="216600"/></a:xfrm><a:prstGeom prst="rect"><a:avLst/></a:prstGeom><a:noFill/><a:ln><a:noFill/></a:ln></p:spPr><p:txBody><a:bodyPr anchorCtr="0" anchor="ctr" bIns="91425" lIns="91425" spcFirstLastPara="1" rIns="91425" wrap="square" tIns="91425"><a:noAutofit/></a:bodyPr><a:lstStyle/><a:p><a:pPr indent="0" lvl="0" marL="0" rtl="0" algn="l"><a:spcBef><a:spcPts val="0"/></a:spcBef><a:spcAft><a:spcPts val="0"/></a:spcAft><a:buNone/></a:pPr><a:r><a:rPr lang="en" sz="1200"><a:latin typeface="Roboto"/><a:ea typeface="Roboto"/><a:cs typeface="Roboto"/><a:sym typeface="Roboto"/></a:rPr><a:t>10</a:t></a:r><a:endParaRPr sz="1200"><a:latin typeface="Roboto"/><a:ea typeface="Roboto"/><a:cs typeface="Roboto"/><a:sym typeface="Roboto"/></a:endParaRPr></a:p></p:txBody></p:sp><p:sp><p:nvSpPr><p:cNvPr id="458" name="Google Shape;458;p25"/><p:cNvSpPr txBox="1"/><p:nvPr/></p:nvSpPr><p:spPr><a:xfrm><a:off x="8315250" y="3607700"/><a:ext cx="371700" cy="216600"/></a:xfrm><a:prstGeom prst="rect"><a:avLst/></a:prstGeom><a:noFill/><a:ln><a:noFill/></a:ln></p:spPr><p:txBody><a:bodyPr anchorCtr="0" anchor="ctr" bIns="91425" lIns="91425" spcFirstLastPara="1" rIns="91425" wrap="square" tIns="91425"><a:noAutofit/></a:bodyPr><a:lstStyle/><a:p><a:pPr indent="0" lvl="0" marL="0" rtl="0" algn="l"><a:spcBef><a:spcPts val="0"/></a:spcBef><a:spcAft><a:spcPts val="0"/></a:spcAft><a:buNone/></a:pPr><a:r><a:rPr lang="en" sz="1200"><a:latin typeface="Roboto"/><a:ea typeface="Roboto"/><a:cs typeface="Roboto"/><a:sym typeface="Roboto"/></a:rPr><a:t>0</a:t></a:r><a:endParaRPr sz="1200"><a:latin typeface="Roboto"/><a:ea typeface="Roboto"/><a:cs typeface="Roboto"/><a:sym typeface="Roboto"/></a:endParaRPr></a:p></p:txBody></p:sp></p:spTree></p:cSld><p:clrMapOvr><a:masterClrMapping/></p:clrMapOvr></p:sld>